LICENSE.md
MANIFEST.in
README.rst
pyproject.toml
requirements.core.txt
setup.py
core_explore_federated_search_app/__init__.py
core_explore_federated_search_app/settings.py
core_explore_federated_search_app/urls.py
core_explore_federated_search_app.egg-info/PKG-INFO
core_explore_federated_search_app.egg-info/SOURCES.txt
core_explore_federated_search_app.egg-info/dependency_links.txt
core_explore_federated_search_app.egg-info/requires.txt
core_explore_federated_search_app.egg-info/top_level.txt
core_explore_federated_search_app/components/__init__.py
core_explore_federated_search_app/components/data/__init__.py
core_explore_federated_search_app/components/data/api.py
core_explore_federated_search_app/migrations/__init__.py
core_explore_federated_search_app/rest/__init__.py
core_explore_federated_search_app/rest/urls.py
core_explore_federated_search_app/rest/query/__init__.py
core_explore_federated_search_app/rest/query/serializers.py
core_explore_federated_search_app/rest/query/views.py
core_explore_federated_search_app/rest/result/__init__.py
core_explore_federated_search_app/rest/result/serializers.py
core_explore_federated_search_app/rest/result/views.py
core_explore_federated_search_app/static/core_explore_federated_search_app/admin/js/repositories/list/modals/delete.js
core_explore_federated_search_app/static/core_explore_federated_search_app/admin/js/repositories/list/modals/delete.raw.js
core_explore_federated_search_app/static/core_explore_federated_search_app/admin/js/repositories/list/modals/edit.js
core_explore_federated_search_app/static/core_explore_federated_search_app/admin/js/repositories/list/modals/edit.raw.js
core_explore_federated_search_app/static/core_explore_federated_search_app/admin/js/repositories/list/modals/refresh.js
core_explore_federated_search_app/static/core_explore_federated_search_app/admin/js/repositories/list/modals/refresh.raw.js
core_explore_federated_search_app/static/core_explore_federated_search_app/user/js/data_sources/list.js
core_explore_federated_search_app/templates/core_explore_federated_search_app/admin/repositories/add_repository.html
core_explore_federated_search_app/templates/core_explore_federated_search_app/admin/repositories/list_repositories.html
