Metadata-Version: 2.1
Name: core-explore-federated-search-app
Version: 2.19.0
Summary: Federation exploration functions for curator core project
Home-page: https://github.com/usnistgov/core_explore_federated_search_app
Author: NIST IT Lab
Author-email: itl_inquiries@nist.gov
License-File: LICENSE.md
